{
  "schemaVersion": 1,
  "id": "autorelog",
  "version": "${version}",
  "name": "AutoRelog",
  "description": "",
  "authors": [],
  "contact": {
    "repo": "https://github.com/scubakay/AutoRelog"
  },
  "license": "MIT",
  "icon": "assets/autorelog/icon.png",
  "environment": "client",
  "entrypoints": {
    "client": [
      "com.scubakay.autorelog.AutoRelogClient"
    ]
  },
  "mixins": [
    "autorelog.mixins.json"
  ],
  "depends": {
    "fabricloader": ">=${loader_version}",
    "fabric-api": "*",
    "minecraft": "${minecraft_version}"
  }
}
